README
setup.py
kyd/__init__.py
kyd/api.py
kyd.egg-info/PKG-INFO
kyd.egg-info/SOURCES.txt
kyd.egg-info/dependency_links.txt
kyd.egg-info/top_level.txt