Metadata-Version: 1.1
Name: kyd
Version: 0.0.9
Summary: see doc at http://doc.kuaiyutech.com
Home-page: http://packages.python.org/kyd
Author: ShangHai Shilai
Author-email: developers@kuaiyudian.com
License: BSD
Keywords: stock kuaiyudian sdk kyd
Platform: UNKNOWN
Classifier: Development Status :: 3 - Alpha
Classifier: Environment :: Web Environment
Classifier: Intended Audience :: Developers
Classifier: License :: OSI Approved :: BSD License
Classifier: Operating System :: OS Independent
Classifier: Programming Language :: Python
